pytest_freezeblaster/__init__.py
pytest_freezeblaster/py.typed
pytest_freezeblaster-2.1.0.dist-info/WHEEL
pytest_freezeblaster-2.1.0.dist-info/entry_points.txt
pytest_freezeblaster-2.1.0.dist-info/METADATA
pytest_freezeblaster-2.1.0.dist-info/RECORD
